Digital/MUX8_to_1.v
module mux8_to_1 ( in , out , s , en_bar );

output out ;
input [7:0] in ;
input [2:0] s ;
input en_bar ;

wire out_before_z ;
wire [7:0] y ;
wire [2:0] sn ;

not( sn[0] , s[0] ) ;
not( sn[1] , s[1] ) ;
not( sn[2] , s[2] ) ;

and( y[0] , in[0] ,  sn[2] , sn[1] , sn[0] ) ;
and( y[1] , in[1] ,  sn[2] , sn[1] ,  s[0] ) ;
and( y[2] , in[2] ,  sn[2] ,  s[1] , sn[0] ) ;
and( y[3] , in[3] ,  sn[2] ,  s[1] ,  s[0] ) ;
and( y[4] , in[4] ,   s[2] , sn[1] , sn[0] ) ;
and( y[5] , in[5] ,   s[2] , sn[1] ,  s[0] ) ;
and( y[6] , in[6] ,   s[2] ,  s[1] , sn[0] ) ;
and( y[7] , in[7] ,   s[2] ,  s[1] ,  s[0] ) ;

or( out_before_z , y[0] , y[1] , y[2] , y[3] , y[4] , y[5] , y[6] , y[7] ) ;

bufif0( out , out_before_z , en_bar ) ;

endmodule

Digital/MUX8_to_1_TestBench.v
`include "MUX8_to_1.v"

module TestBench;

reg EN_BAR ;
reg [7:0] IN ;
reg [2:0] S ;

wire OUTPUT ;

mux8_to_1 mymux( IN , OUTPUT , S , EN_BAR ) ;

initial
begin

$dumpfile("MUX8_to_1.vcd");
$dumpvars;

IN[0] = 1 ; IN[1] = 1 ; IN[2] = 0 ; IN[3] = 1 ; IN[4] = 0 ; IN[5] = 1 ; IN[6] = 0 ; IN[7] = 1 ;

EN_BAR = 1 ;

   S[2] = 0 ; S[1] = 0 ; S[0] = 0 ;
#5 S[2] = 0 ; S[1] = 0 ; S[0] = 1 ;
#5 S[2] = 0 ; S[1] = 1 ; S[0] = 0 ;
#5 S[2] = 0 ; S[1] = 1 ; S[0] = 1 ;
#5 S[2] = 1 ; S[1] = 0 ; S[0] = 0 ;
#5 S[2] = 1 ; S[1] = 0 ; S[0] = 1 ;
#5 S[2] = 1 ; S[1] = 1 ; S[0] = 0 ;
#5 S[2] = 1 ; S[1] = 1 ; S[0] = 1 ;
#5;

EN_BAR = 0 ;

   S[2] = 0 ; S[1] = 0 ; S[0] = 0 ;
#5 S[2] = 0 ; S[1] = 0 ; S[0] = 1 ;
#5 S[2] = 0 ; S[1] = 1 ; S[0] = 0 ;
#5 S[2] = 0 ; S[1] = 1 ; S[0] = 1 ;
#5 S[2] = 1 ; S[1] = 0 ; S[0] = 0 ;
#5 S[2] = 1 ; S[1] = 0 ; S[0] = 1 ;
#5 S[2] = 1 ; S[1] = 1 ; S[0] = 0 ;
#5 S[2] = 1 ; S[1] = 1 ; S[0] = 1 ;
#5;

end
endmodule

Digital/MUX8_to_1.vcd
$date
	Sun Aug 27 15:47:04 2023
$end
$version
	Icarus Verilog
$end
$timescale
	1s
$end
$scope module TestBench $end
$var wire 1 ! OUTPUT $end
$var reg 1 " EN_BAR $end
$var reg 8 # IN [7:0] $end
$var reg 3 $ S [2:0] $end
$scope module mymux $end
$var wire 1 " en_bar $end
$var wire 8 % in [7:0] $end
$var wire 1 ! out $end
$var wire 1 & out_before_z $end
$var wire 3 ' s [2:0] $end
$var wire 8 ( y [7:0] $end
$var wire 3 ) sn [2:0] $end
$upscope $end
$upscope $end
$enddefinitions $end
$comment Show the parameter values. $end
$dumpall
$end
#0
$dumpvars
b111 )
b1 (
b0 '
1&
b10101011 %
b0 $
b10101011 #
1"
z!
$end
#5
b110 )
b10 (
b1 $
b1 '
#10
z!
0&
b0 (
b101 )
b10 $
b10 '
#15
z!
1&
b100 )
b1000 (
b11 $
b11 '
#20
z!
0&
b0 (
b11 )
b100 $
b100 '
#25
z!
1&
b10 )
b100000 (
b101 $
b101 '
#30
z!
0&
b0 (
b1 )
b110 $
b110 '
#35
z!
1&
b0 )
b10000000 (
b111 $
b111 '
#40
1&
b111 )
b1 (
b0 $
b0 '
1!
0"
#45
b110 )
b10 (
b1 $
b1 '
#50
0!
0&
b0 (
b101 )
b10 $
b10 '
#55
1!
1&
b100 )
b1000 (
b11 $
b11 '
#60
0!
0&
b0 (
b11 )
b100 $
b100 '
#65
1!
1&
b10 )
b100000 (
b101 $
b101 '
#70
0!
0&
b0 (
b1 )
b110 $
b110 '
#75
1!
1&
b0 )
b10000000 (
b111 $
b111 '
